SupremeUtils/__init__.py
SupremeUtils/ascii.py
SupremeUtils/terminal_color.py
SupremeUtils-0.0.2.dist-info/LICENSE.txt
SupremeUtils-0.0.2.dist-info/METADATA
SupremeUtils-0.0.2.dist-info/WHEEL
SupremeUtils-0.0.2.dist-info/top_level.txt
SupremeUtils-0.0.2.dist-info/RECORD
