Metadata-Version: 2.1
Name: SupremeUtils
Version: 0.0.2
Summary: A package full of great utility functions
Home-page: https://github.com/SystemFalll/SupremeUtils
Author: SystemFall
Author-email: systemfallbusiness@gmail.com
License: UNKNOWN
Project-URL: Bug Tracker, https://github.com/SystemFalll/SupremeUtils/issues
Platform: UNKNOWN
Classifier: Programming Language :: Python :: 3
Classifier: License :: OSI Approved :: GNU General Public License (GPL)
Classifier: Operating System :: OS Independent
Requires-Python: >=3.6
License-File: LICENSE.txt
